Metadata-Version: 2.1
Name: biscuit-py-prima-airflow
Version: 0.1.0
Summary: biscuit-py decrypts secrets managed by Biscuit. Credits to Doug Coker.
Home-page: https://github.com/primait/biscuit-py
Author: Prima Assicurazioni Data Team
Author-email: team-data@prima.it
License: https://www.apache.org/licenses/LICENSE-2.0
Classifier: Development Status :: 4 - Beta
Classifier: Intended Audience :: Developers
Classifier: License :: OSI Approved :: Apache Software License
Classifier: Programming Language :: Python :: 3.7
License-File: LICENSE
